arduinobootloader.py
arduinobootloader-0.0.6.dist-info/LICENSE
arduinobootloader-0.0.6.dist-info/METADATA
arduinobootloader-0.0.6.dist-info/WHEEL
arduinobootloader-0.0.6.dist-info/top_level.txt
arduinobootloader-0.0.6.dist-info/RECORD
