Metadata-Version: 2.1
Name: arduinobootloader
Version: 0.0.6
Summary: Update the firmware of Arduino boards based on Atmel AVR
Home-page: https://github.com/jjsch-dev/PyArduinoFlash
Author: Juan Schiavoni
Author-email: juanschiavoni@gmail.com
License: MIT
Keywords: arduino,flash,bootloader,upgrade
Platform: UNKNOWN
Classifier: Development Status :: 3 - Alpha
Classifier: Environment :: Console
Classifier: Intended Audience :: Developers
Classifier: License :: OSI Approved :: MIT License
Classifier: Operating System :: OS Independent
Classifier: Programming Language :: Python :: 3
Classifier: Programming Language :: Python :: 3.2
Classifier: Programming Language :: Python :: 3.3
Classifier: Programming Language :: Python :: 3.4
Classifier: Programming Language :: Python :: 3.5
Classifier: Programming Language :: Python :: 3.6
Classifier: Programming Language :: Python :: 3.7
Requires-Python: >=3
Requires-Dist: pyserial (>=3.4)
